impulse/__init__.py
impulse/adapters.py
impulse/cli.py
impulse/dotfile.py
impulse/ports.py
impulse/py.typed
impulse/application/__init__.py
impulse/application/use_cases.py
impulse-2.2.dist-info/METADATA
impulse-2.2.dist-info/WHEEL
impulse-2.2.dist-info/entry_points.txt
impulse-2.2.dist-info/licenses/AUTHORS.rst
impulse-2.2.dist-info/licenses/LICENSE
impulse-2.2.dist-info/RECORD
